{
  "_readme": "بنك أفكار مقترح (30 فكرة) لقناة بوبو وفستق. يقرأه bobo-festuk-episode-generator (STEP 3d) كأولوية قبل ارتجال فكرة جديدة. كل فكرة فيها used=false حتى تُستخدم، ثم تصير true. الشخصيات: bobo, festuk, arnouba. الفئة تتبع نسب المحتوى المعتمدة (40% مغامرات/تشويق، 20% كوميديا، 15% ألغاز، 15% تعليم غير مباشر، 10% قيم وأخلاق).",
  "ideas": [
    {"id": 1, "used": false, "series": "مغامرات بوبو وفستق", "category": "مغامرة/تشويق", "characters": ["bobo","festuk"], "name": "الصندوق الغامض في الغابة", "hook": "بوبو يفتح صندوقًا مدفونًا فجأة ينبعث منه ضوء أخضر غريب", "type": "Short", "duration": "35-40 ثانية", "story": "بوبو يجد صندوقًا خشبيًا مدفونًا تحت الأوراق، وفستق يحاول منعه من فتحه بسرعة", "surprise": "الضوء الغريب مصدره مجموعة يراعات نائمة استيقظت", "ending": "الاثنان يطلقان اليراعات معًا وتضيء الغابة حولهما بمشهد ساحر", "title": "بوبو فتح الصندوق الممنوع… وشاهد ما بداخله! 😨", "alt_title": "ضوء غريب يخرج من صندوق مدفون بالغابة!", "thumbnail": "بوبو خائف ومتفاجئ، خلفه صندوق مفتوح يخرج منه ضوء أخضر، فستق ينظر بدهشة"},
    {"id": 2, "used": false, "series": "مغامرات بوبو وفستق", "category": "كوميديا", "characters": ["bobo","festuk"], "name": "سباق أوراق الخريف", "hook": "بوبو ينزلق فجأة على كومة أوراق ويتدحرج بسرعة نحو المنحدر", "type": "Short", "duration": "30 ثانية", "story": "بوبو وفستق يتسابقان بالتزلج على أكوام الأوراق أسفل التل", "surprise": "فستق يفوز بالصدفة بعدما يعلق بوبو داخل كومة أوراق ضخمة", "ending": "بوبو يخرج من الكومة مغطى بالكامل بالأوراق ويضحك الاثنان معًا", "title": "بوبو انزلق ولم يتوقف! 😂 من سيفوز بالسباق؟", "alt_title": "سباق مجنون على أوراق الخريف!", "thumbnail": "بوبو يتطاير بالهواء فوق كومة أوراق، فستق يضحك بالخلفية"},
    {"id": 3, "used": false, "series": "ألغاز الغابة", "category": "ألغاز وغموض", "characters": ["bobo","festuk"], "name": "لغز الأثر الكبير", "hook": "فستق يكتشف أثر قدم عملاقًا غريبًا بجانب الشجرة", "type": "Short", "duration": "40 ثانية", "story": "الاثنان يتتبعان أثرًا ضخمًا بالغابة ظنًا منهما أنه لمخلوق كبير مخيف", "surprise": "الأثر يعود لظل شجرة قديمة تشبه قدمًا ضخمة عند غروب الشمس", "ending": "يضحكان من خوفهما ويقرران استكشاف المزيد من ظلال الغابة الغريبة", "title": "أثر قدم عملاق بالغابة! 😱 لمن يعود؟", "alt_title": "مخلوق ضخم يمشي بالغابة… أم لا؟", "thumbnail": "فستق ينظر بذهول لأثر قدم ضخم على الأرض، بوبو خلفه متوتر"},
    {"id": 4, "used": false, "series": "تحديات أرنوبة", "category": "مغامرة/تشويق", "characters": ["arnouba","bobo"], "name": "تحدي القفز فوق النهر", "hook": "أرنوبة تقف على حافة النهر وتستعد لقفزة كبيرة جدًا", "type": "Short", "duration": "35 ثانية", "story": "أرنوبة تتحدى نفسها بالقفز فوق النهر الواسع أمام بوبو المتوتر", "surprise": "تسقط بالماء لكنها تكتشف أن الماء ضحل ومليء بأسماك ملونة", "ending": "تقرر اللعب بالماء بدل القفز، وتدعو بوبو للانضمام إليها", "title": "أرنوبة تقفز فوق النهر الكبير! هل نجحت؟", "alt_title": "تحدي مجنون: القفز فوق أوسع نهر بالغابة", "thumbnail": "أرنوبة بمنتصف القفزة بالهواء فوق النهر، بوبو ينظر بقلق من الحافة"},
    {"id": 5, "used": false, "series": "مغامرات بوبو وفستق", "category": "كوميديا", "characters": ["bobo","festuk"], "name": "العسل المسروق", "hook": "بوبو يمد يده لخلية نحل ضخمة معلقة على شجرة", "type": "Short", "duration": "35 ثانية", "story": "بوبو يحاول أخذ العسل بينما فستق يحذره من النحل", "surprise": "النحل يطارد بوبو حول الغابة كاملة بينما فستق يشاهد ضاحكًا", "ending": "بوبو يقفز بالبحيرة هربًا من النحل، ويخرج العسل يلاحقه على وجهه", "title": "النحل طارد بوبو بكل الغابة! 😂 هل نجا؟", "alt_title": "بوبو سرق العسل… ودفع الثمن!", "thumbnail": "بوبو يركض مذعورًا وسحابة نحل خلفه، فستق يضحك من بعيد"},
    {"id": 6, "used": false, "series": "مغامرات بوبو وفستق", "category": "مغامرة/تشويق", "characters": ["bobo","festuk"], "name": "الكهف المظلم", "hook": "الاثنان يدخلان فجأة كهفًا مظلمًا هربًا من المطر", "type": "Short", "duration": "40 ثانية", "story": "بوبو وفستق يستكشفان كهفًا مظلمًا ويسمعان صوتًا غريبًا بالداخل", "surprise": "الصوت الغريب مصدره صدى قطرات الماء المتساقطة من سقف الكهف", "ending": "يكتشفان بلورات متلألئة بقعر الكهف وتضيء المكان بجمال", "title": "صوت غريب بالكهف المظلم! 😨 شو كان؟", "alt_title": "بوبو وفستق علقوا بكهف مرعب!", "thumbnail": "بوبو وفستق متجمدان بالخوف بمدخل كهف مظلم، عيونهما واسعة"},
    {"id": 7, "used": false, "series": "أسرار الغابة المضيئة", "category": "مغامرة/تشويق", "characters": ["bobo","festuk"], "name": "سر الغابة المضيئة - الجزء 1: الخريطة الغريبة", "hook": "ريح قوية تطير خريطة قديمة مباشرة أمام وجه بوبو", "type": "Short", "duration": "40 ثانية", "story": "بوبو يجد خريطة غامضة برموز مضيئة ويقرر تتبعها مع فستق", "surprise": "الخريطة ترسم طريقًا يؤدي مباشرة نحو جزء لم يستكشفاه من الغابة", "ending": "يصلان لباب حجري قديم مغطى بنباتات متسلقة ويقرران العودة غدًا لفتحه", "title": "خريطة غامضة تقود بوبو لمكان مجهول! 😲", "alt_title": "سر الغابة المضيئة يبدأ هنا…", "thumbnail": "بوبو يمسك خريطة مضيئة برموز غريبة، فستق ينظر بفضول فوق كتفه"},
    {"id": 8, "used": false, "series": "أسرار الغابة المضيئة", "category": "مغامرة/تشويق", "characters": ["bobo","festuk"], "name": "سر الغابة المضيئة - الجزء 2: الباب السري", "hook": "بوبو يدفع الباب الحجري القديم فجأة ويُفتح بصوت عالٍ", "type": "Short", "duration": "40 ثانية", "story": "الاثنان يحاولان فتح الباب الحجري المغطى بالنباتات من الجزء السابق", "surprise": "خلف الباب درج حجري ينزل إلى ممر مضاء بضوء أزرق خافت", "ending": "ينزلان بضع درجات بحذر ويريان بريقًا بعيدًا يلمع بآخر الممر", "title": "الباب السري انفتح أخيرًا! ماذا بالداخل؟", "alt_title": "خلف الباب الحجري… مفاجأة مضيئة", "thumbnail": "بوبو وفستق ينظران لباب حجري مفتوح ودرج ينزل بضوء أزرق"},
    {"id": 9, "used": false, "series": "أسرار الغابة المضيئة", "category": "مغامرة/تشويق", "characters": ["bobo","festuk"], "name": "سر الغابة المضيئة - الجزء 3: المعبر المتصدع", "hook": "الأرض تهتز فجأة تحت أقدامهما داخل الممر تحت الأرض", "type": "Short", "duration": "40 ثانية", "story": "الممر يتصدع ويجبرهما على عبور شق ضيق بحذر شديد", "surprise": "أرضية الممر مصنوعة من جسر خشبي قديم متهالك فوق هوة عميقة", "ending": "يعبران بنجاح بالتعاون، وفستق يمسك بوبو من السقوط في اللحظة الأخيرة", "title": "الأرض اهتزت تحتهما فجأة! 😱 نجيا؟", "alt_title": "معبر مهتز يهدد بوبو وفستق تحت الأرض!", "thumbnail": "بوبو يترنح فوق شق بالأرض، فستق يمد يده لإنقاذه بتعبير مرعوب"},
    {"id": 10, "used": false, "series": "أسرار الغابة المضيئة", "category": "مغامرة/تشويق", "characters": ["bobo","festuk"], "name": "سر الغابة المضيئة - الجزء 4: المخلوق الغامض", "hook": "ظل كبير يتحرك فجأة خلف بلورة مضيئة بنهاية الممر", "type": "Short", "duration": "40 ثانية", "story": "الاثنان يقتربان من الضوء البعيد ويريان ظلًا يتحرك خلف صخرة كبيرة", "surprise": "الظل المخيف عبارة عن بومة كبيرة ودودة تحرس المكان منذ سنين", "ending": "البومة تطمئنهما بإيماءة ودودة وتقودهما بجناحها نحو مصدر الضوء", "title": "مخلوق غامض يظهر بآخر الممر! 😨", "alt_title": "من يحرس سر الغابة المضيئة؟", "thumbnail": "عينان كبيرتان تلمعان بالظلام خلف بوبو وفستق المذعورين"},
    {"id": 11, "used": false, "series": "أسرار الغابة المضيئة", "category": "مغامرة/تشويق", "characters": ["bobo","festuk"], "name": "سر الغابة المضيئة - الجزء 5: سر الضوء", "hook": "البومة تكشف فجأة عن غرفة مليئة بالبلورات المتلألئة", "type": "Short", "duration": "40 ثانية", "story": "بوبو وفستق يصلان أخيرًا لمصدر الضوء الذي كانت الخريطة تقودهما إليه", "surprise": "الضوء مصدره حديقة بلورات طبيعية تنمو منذ مئات السنين وتضيء الغابة ليلًا", "ending": "يقرران حماية سر المكان وعدم إخبار أحد، ويعودان بابتسامة رضا كبيرة", "title": "أخيرًا… سر الغابة المضيئة انكشف! ✨", "alt_title": "ما وجده بوبو وفستق غيّر كل شيء", "thumbnail": "بوبو وفستق يقفان مذهولين وسط غرفة بلورات متوهجة بألوان زاهية"},
    {"id": 12, "used": false, "series": "تحديات أرنوبة", "category": "مغامرة/تشويق", "characters": ["arnouba","bobo","festuk"], "name": "أرنوبة والتحدي الكبير: سباق الأشجار", "hook": "أرنوبة تقفز فجأة من غصن لآخر بسرعة مذهلة أمام الاثنين", "type": "Short", "duration": "35 ثانية", "story": "أرنوبة تتحدى بوبو وفستق بسباق قفز بين أغصان الأشجار العالية", "surprise": "فستق الصغير يفوز بفضل خفة وزنه رغم تفوق أرنوبة بالمهارة", "ending": "الثلاثة يضحكون معًا ويتفقون على إعادة السباق أسبوعيًا", "title": "أرنوبة تتحدى الجميع بسباق الأشجار! من فاز؟", "alt_title": "سباق قفز جنوني بين أعالي الأشجار!", "thumbnail": "أرنوبة معلقة بمنتصف قفزة بين غصنين، بوبو وفستق يراقبان بدهشة"},
    {"id": 13, "used": false, "series": "مغامرات بوبو وفستق", "category": "مغامرة/تشويق", "characters": ["bobo","festuk"], "name": "المطر المفاجئ", "hook": "سحابة سوداء ضخمة تحجب الشمس فجأة وتبدأ الأمطار بغزارة", "type": "Short", "duration": "30 ثانية", "story": "بوبو وفستق يحاولان بناء مأوى سريع من الأوراق والأغصان قبل أن يبتلا تمامًا", "surprise": "المأوى ينهار عليهما مباشرة بعد إتمامه بثانية واحدة", "ending": "يقرران الرقص تحت المطر بدل الاختباء منه ويستمتعان بوقتهما", "title": "مطر مفاجئ يهاجم بوبو وفستق! 😆", "alt_title": "سباق ضد المطر… وخسارة مضحكة!", "thumbnail": "بوبو وفستق مبتلان تمامًا وسقف المأوى ينهار فوقهما"},
    {"id": 14, "used": false, "series": "مغامرات بوبو وفستق", "category": "تعليم غير مباشر", "characters": ["bobo","festuk"], "name": "الفراشة النادرة", "hook": "فراشة بألوان غريبة جدًا تحط فجأة على أنف بوبو", "type": "Short", "duration": "35 ثانية", "story": "بوبو يحاول الإمساك بالفراشة النادرة بينما فستق يحاول إقناعه بمراقبتها فقط", "surprise": "محاولات الإمساك تخيف الفراشة أكثر، بينما الهدوء يجعلها تقترب بنفسها", "ending": "الفراشة تحط على يد بوبو الهادئة بعدما توقف عن المطاردة", "title": "فراشة نادرة تهرب من بوبو! كيف أمسك بها؟", "alt_title": "سر الإمساك بالفراشة النادرة!", "thumbnail": "فراشة ملونة على أنف بوبو المتفاجئ، فستق يبتسم بالخلفية"},
    {"id": 15, "used": false, "series": "ألغاز الغابة", "category": "ألغاز وغموض", "characters": ["bobo","festuk"], "name": "صندوق الألغاز الخشبي", "hook": "فستق يجد صندوقًا خشبيًا صغيرًا مقفلًا بثلاث حلقات دوارة", "type": "Short", "duration": "40 ثانية", "story": "الاثنان يحاولان حل شفرة الصندوق الغريب المكون من رموز حيوانات", "surprise": "الحل يعتمد ترتيب الحيوانات حسب حجمها، وليس عشوائيًا كما ظنا", "ending": "الصندوق يفتح عن مجموعة بذور نادرة يزرعانها معًا بالغابة", "title": "صندوق ألغاز غامض بالغابة! كيف نفتحه؟", "alt_title": "شفرة سرية تحتاج حلًا ذكيًا!", "thumbnail": "فستق يدرس صندوقًا خشبيًا برموز حيوانات، بوبو يخمن بحيرة"},
    {"id": 16, "used": false, "series": "ألغاز الغابة", "category": "كوميديا", "characters": ["bobo","festuk"], "name": "من أخذ التوت؟", "hook": "بوبو يصل لمخبأ توته السري ويجده فارغًا تمامًا", "type": "Short", "duration": "30 ثانية", "story": "بوبو يحقق بغضب مع فستق عن هوية من أكل توته المخفي", "surprise": "الفاعل الحقيقي طائر صغير كان يسرق التوت طوال الأسبوع", "ending": "بوبو يضع فخًا بسيطًا للطائر لكنه يقع فيه هو بنفسه بالخطأ", "title": "من سرق توت بوبو السري؟! 🕵️", "alt_title": "لغز التوت المفقود!", "thumbnail": "بوبو يحدق بمخبأ فارغ بصدمة، فستق يشير لريشة صغيرة بجانبه"},
    {"id": 17, "used": false, "series": "مغامرات بوبو وفستق", "category": "كوميديا", "characters": ["bobo","festuk"], "name": "عالق على الشجرة", "hook": "بوبو يتسلق شجرة بسرعة هربًا من شيء ما ويعلق بأعلى غصن", "type": "Short", "duration": "35 ثانية", "story": "فستق يحاول إيجاد طريقة لإنزال بوبو العالق دون أن يسقط", "surprise": "الشيء الذي كان بوبو يهرب منه كان مجرد أرنب صغير ودود", "ending": "بوبو ينزل أخيرًا بمساعدة أغصان مطاطية ويضحك من خوفه الزائد", "title": "بوبو علق بأعلى الشجرة! كيف سينزل؟", "alt_title": "هرب من لا شيء… وعلق بكل شيء!", "thumbnail": "بوبو متشبث بأعلى غصن بخوف، فستق ينظر للأعلى بقلق"},
    {"id": 18, "used": false, "series": "مغامرات بوبو وفستق", "category": "مغامرة/تشويق", "characters": ["bobo","festuk"], "name": "سباق الزلاجة الثلجية", "hook": "بوبو يقفز فجأة على زلاجة ثلجية مرتجلة وينطلق بسرعة كبيرة", "type": "Short", "duration": "35 ثانية", "story": "أول ثلوج بالغابة تدفع بوبو وفستق لتجربة التزلج المرتجل من أعلى التل", "surprise": "الزلاجة تنحرف فجأة نحو بحيرة متجمدة صغيرة", "ending": "تتوقف الزلاجة قبل الجليد الرقيق بلحظات، وينفجران ضحكًا من الموقف", "title": "زلاجة بوبو انطلقت بلا توقف! 😱", "alt_title": "أول تزلج لبوبو… يكاد ينتهي بكارثة!", "thumbnail": "بوبو على زلاجة مرتجلة بسرعة كبيرة، فستق يركض خلفه بذعر"},
    {"id": 19, "used": false, "series": "مغامرات بوبو وفستق", "category": "كوميديا", "characters": ["bobo","festuk"], "name": "الضفدع العملاق المخادع", "hook": "صوت نقيق ضخم جدًا يهز الأرض فجأة أمام الاثنين", "type": "Short", "duration": "30 ثانية", "story": "بوبو وفستق يظنان أن ضفدعًا عملاقًا يقترب منهما بخوف شديد", "surprise": "الصوت كان لضفدع صغير جدًا ينقّق داخل صدفة كبيرة تضخم الصوت", "ending": "يضحكان ويأخذان الصدفة للعب بها وتضخيم أصواتهما هما أيضًا", "title": "ضفدع عملاق يهز الغابة! أم لا؟ 😂", "alt_title": "صوت مرعب مصدره أصغر مخلوق!", "thumbnail": "بوبو وفستق متجمدان بالخوف، وصدفة كبيرة أمامهما تصدر أمواجًا صوتية"},
    {"id": 20, "used": false, "series": "مغامرات بوبو وفستق", "category": "قيم وأخلاق", "characters": ["bobo","festuk"], "name": "مساعدة الطائر الصغير", "hook": "طائر صغير يسقط فجأة من عشه أمام بوبو وفستق", "type": "Short", "duration": "35 ثانية", "story": "الاثنان يحاولان إعادة الطائر الصغير لعشه العالي بأي طريقة ممكنة", "surprise": "محاولات الرمي والتسلق تفشل، فيبنيان سلمًا مؤقتًا من الأغصان", "ending": "الطائر يعود لعشه بأمان وأمه تشكرهما بتحليقة قريبة منهما", "title": "طائر صغير بحاجة للمساعدة! هل ينجحان؟", "alt_title": "مهمة إنقاذ الطائر الصغير!", "thumbnail": "بوبو يحمل فرخ طائر بحذر بيديه، فستق يبني سلمًا من الأغصان"},
    {"id": 21, "used": false, "series": "مغامرات بوبو وفستق", "category": "مغامرة/تشويق", "characters": ["bobo","festuk"], "name": "القارب الورقي", "hook": "قارب ورقي صغير صنعه بوبو ينجرف فجأة بتيار النهر بسرعة", "type": "Short", "duration": "35 ثانية", "story": "بوبو وفستق يجريان بمحاذاة النهر لإنقاذ القارب الورقي قبل الشلال", "surprise": "يمسكان القارب أخيرًا لكنهما يكتشفان رسالة صغيرة كتبها بوبو بالداخل", "ending": "يقرران إرسال القارب مجددًا عمدًا هذه المرة ليرَ أين سينتهي به المطاف", "title": "قارب ورقي يتجه نحو الشلال! 😱", "alt_title": "سباق ضد النهر لإنقاذ القارب!", "thumbnail": "قارب ورقي صغير بمنتصف نهر متدفق، بوبو وفستق يركضان بمحاذاته"},
    {"id": 22, "used": false, "series": "ألغاز الغابة", "category": "ألغاز وغموض", "characters": ["bobo","festuk"], "name": "صدى الغابة الغريب", "hook": "صدى غريب يكرر كلمات لم يقلها أحد وسط الغابة الهادئة", "type": "Short", "duration": "35 ثانية", "story": "بوبو وفستق يتتبعان مصدر الصدى الغامض بين الصخور الكبيرة", "surprise": "الصدى ناتج عن تشكيلة صخرية طبيعية تعكس الأصوات بقوة", "ending": "يقضيان بقية اليوم يلعبان بالصدى ويصرخان أسماءهما ضاحكين", "title": "صدى غريب بالغابة يخيف الجميع! 😨", "alt_title": "من يتكلم بالغابة الهادئة؟", "thumbnail": "بوبو وفستق يستمعان بحذر قرب صخور كبيرة، تعبير حيرة على وجهيهما"},
    {"id": 23, "used": false, "series": "مغامرات بوبو وفستق", "category": "قيم وأخلاق", "characters": ["bobo","festuk"], "name": "تبادل الأدوار ليوم واحد", "hook": "بوبو وفستق يتشاجران فجأة حول من مهمته أصعب باليوم", "type": "Short", "duration": "40 ثانية", "story": "يقرران تبادل الأدوار ليوم واحد: بوبو يخطط بحذر وفستق يغامر باندفاع", "surprise": "كل واحد يفشل بدور الآخر ويدرك صعوبة ما كان يستهين به", "ending": "يعودان لأدوارهما الأصلية لكن بتقدير أكبر لبعضهما البعض", "title": "بوبو وفستق بدّلا الأدوار! ماذا حدث؟", "alt_title": "يوم واحد بمكان الآخر… فوضى مضحكة!", "thumbnail": "بوبو يحاول التخطيط بحذر مبالغ فيه، فستق يقفز باندفاع، الاثنان بارتباك"},
    {"id": 24, "used": false, "series": "مغامرات بوبو وفستق", "category": "مغامرة/تشويق", "characters": ["bobo","festuk"], "name": "الفخ المخفي", "hook": "بوبو يخطو فجأة على أرضية مموهة بأوراق فتنهار تحته", "type": "Short", "duration": "35 ثانية", "story": "بوبو يسقط بحفرة قديمة مموهة بينما يحاول فستق سحبه للأعلى", "surprise": "قاع الحفرة مليء بجذور طرية تجعل السقوط ممتعًا كالنطاطة", "ending": "يقرران تحويل الحفرة إلى ملعب قفز آمن بدل تركها فخًا خطيرًا", "title": "الأرض ابتلعت بوبو فجأة! 😱", "alt_title": "فخ مخفي بالغابة… ونهاية مضحكة!", "thumbnail": "بوبو يسقط بحفرة مموهة بالأوراق، فستق يمد يده مرعوبًا"},
    {"id": 25, "used": false, "series": "مغامرات بوبو وفستق", "category": "تعليم غير مباشر", "characters": ["bobo","festuk"], "name": "سباق جمع الجوز قبل الشتاء", "hook": "فستق يلاحظ فجأة أوراق الأشجار تتساقط بسرعة وينطلق مذعورًا", "type": "Short", "duration": "35 ثانية", "story": "فستق يحاول جمع أكبر قدر من الجوز قبل الشتاء بينما بوبو يلهو دون تخطيط", "surprise": "الشتاء يصل مبكرًا فعلًا وبوبو يجد نفسه بلا مؤونة", "ending": "فستق يشارك بوبو مؤونته ويعلمانه معًا كيف يخطط للمستقبل", "title": "الشتاء اقترب! هل استعد فستق بالوقت الكافي؟", "alt_title": "سباق ضد الزمن قبل الشتاء!", "thumbnail": "فستق يجمع الجوز بسرعة جنونية، بوبو يتفرج بلا اكتراث بالخلفية"},
    {"id": 26, "used": false, "series": "تحديات أرنوبة", "category": "قيم وأخلاق", "characters": ["arnouba","bobo"], "name": "أرنوبة تتحدى الخوف: الظلام الكبير", "hook": "الأضواء تختفي فجأة وأرنوبة تقف وحيدة أمام كهف مظلم", "type": "Short", "duration": "40 ثانية", "story": "أرنوبة تتحدى خوفها من الظلام لتساعد بوبو العالق بالداخل", "surprise": "تكتشف أن الظلام كان مخيفًا بمخيلتها أكثر من الواقع", "ending": "تدخل بثقة وتخرج بوبو، ويحتفلان بتغلبها على خوفها", "title": "أرنوبة تواجه أكبر خوف لها! 😨", "alt_title": "الظلام لم يعد مخيفًا بعد اليوم!", "thumbnail": "أرنوبة تقف بحزم أمام مدخل كهف مظلم، عيناها مصممتان رغم الخوف"},
    {"id": 27, "used": false, "series": "ألغاز الغابة", "category": "تعليم غير مباشر", "characters": ["bobo","festuk"], "name": "الفطر الغريب", "hook": "بوبو يمد يده بسرعة نحو فطر ملون غريب الشكل", "type": "Short", "duration": "35 ثانية", "story": "فستق يوقف بوبو بحزم قبل لمس الفطر المجهول ويقترحان مراقبته من بعيد بدلًا من ذلك", "surprise": "يكتشفان أن الفطر يتوهج ليلًا ويجذب حشرات نافعة للغابة", "ending": "يتفقان على تعليم قاعدة جديدة: لا تلمس ما لا تعرفه، راقبه أولاً", "title": "فطر غريب بالغابة… هل يجب لمسه؟", "alt_title": "سر الفطر المتوهج!", "thumbnail": "بوبو يمد يده بحذر نحو فطر ملون، فستق يوقفه بإشارة يد"},
    {"id": 28, "used": false, "series": "مغامرات بوبو وفستق", "category": "مغامرة/تشويق", "characters": ["bobo","festuk"], "name": "اختفاء فستق المفاجئ", "hook": "بوبو يستدير فجأة ولا يجد فستق بجانبه إطلاقًا", "type": "Short", "duration": "40 ثانية", "story": "بوبو يبحث بذعر متزايد عن فستق المفقود بأنحاء الغابة", "surprise": "فستق كان محشورًا داخل جذع شجرة مجوف يحاول الوصول لعش عصفور", "ending": "بوبو يسحبه بحذر ويتعانقان بفرح شديد بعد الخوف الكبير", "title": "فستق اختفى فجأة! 😱 أين ذهب؟", "alt_title": "بحث محموم عن فستق المفقود!", "thumbnail": "بوبو يبحث بذعر وسط الغابة، مكان فستق فارغ بجانبه"},
    {"id": 29, "used": false, "series": "مغامرات بوبو وفستق", "category": "كوميديا", "characters": ["bobo","festuk"], "name": "البالون الطائر الهارب", "hook": "بالون ملون كبير يفلت فجأة من يد بوبو ويطير للأعلى", "type": "Short", "duration": "30 ثانية", "story": "بوبو وفستق يحاولان اللحاق بالبالون قبل أن يختفي بين الأشجار العالية", "surprise": "البالون يعلق أخيرًا بعش طائر كبير ليصبح زينة جديدة للعش", "ending": "الطائر يبدو سعيدًا جدًا بزينته الجديدة فيتركانه له كهدية", "title": "بالون بوبو هرب للسماء! هل سيلحق به؟", "alt_title": "مطاردة طائرة لبالون هارب!", "thumbnail": "بالون كبير يطير للأعلى، بوبو يقفز محاولًا الإمساك به وفستق يراقب"},
    {"id": 30, "used": false, "series": "مغامرات بوبو وفستق", "category": "قيم وأخلاق", "characters": ["bobo","festuk","arnouba"], "name": "عيد الغابة السنوي", "hook": "زينة ملونة تتساقط فجأة من الأشجار معلنة بدء احتفال الغابة", "type": "Short", "duration": "40 ثانية", "story": "الأصدقاء الثلاثة يجهزون معًا لاحتفال الغابة السنوي رغم مشاكل صغيرة بالتحضير", "surprise": "كل شيء يكاد ينهار قبل الحفل، لكن تعاونهم بآخر لحظة ينقذ الموقف", "ending": "يحتفلون معًا بنجاح اليوم، ويحتفون بصداقتهم أكثر من الزينة نفسها", "title": "هل ينجح عيد الغابة قبل فوات الأوان؟", "alt_title": "احتفال الغابة الكبير يوشك أن ينهار!", "thumbnail": "بوبو وفستق وأرنوبة يحملون زينة ملونة بحماس وسط الغابة المزينة"}
  ]
}
